demmsoo/__init__.py
demmsoo-0.0.1.dist-info/licenses/LICENSE
demmsoo-0.0.1.dist-info/METADATA
demmsoo-0.0.1.dist-info/WHEEL
demmsoo-0.0.1.dist-info/top_level.txt
demmsoo-0.0.1.dist-info/RECORD
