Metadata-Version: 2.4
Name: demmsoo
Version: 0.0.1
Summary: Demmsoo - Coming soon!
Author-email: ilCasti <matteocastiglionidev@gmail.com>
Project-URL: Homepage, https://github.com/demmsoo/demmsoo-py
Project-URL: Bug Tracker, https://github.com/demmsoo/demmsoo-py/issues
Classifier: Development Status :: 1 - Planning
Classifier: Intended Audience :: Developers
Classifier: Programming Language :: Python :: 3
Classifier: Programming Language :: Python :: 3.7
Classifier: Programming Language :: Python :: 3.8
Classifier: Programming Language :: Python :: 3.9
Classifier: Programming Language :: Python :: 3.10
Classifier: Programming Language :: Python :: 3.11
Classifier: Programming Language :: Python :: 3.12
Requires-Python: >=3.7
License-File: LICENSE
Dynamic: license-file
